fhir_types/FHIR_Account.py
fhir_types/FHIR_Account_Coverage.py
fhir_types/FHIR_Account_Guarantor.py
fhir_types/FHIR_ActivityDefinition.py
fhir_types/FHIR_ActivityDefinition_DynamicValue.py
fhir_types/FHIR_ActivityDefinition_Participant.py
fhir_types/FHIR_Address.py
fhir_types/FHIR_AdverseEvent.py
fhir_types/FHIR_AdverseEvent_Causality.py
fhir_types/FHIR_AdverseEvent_SuspectEntity.py
fhir_types/FHIR_Age.py
fhir_types/FHIR_AllergyIntolerance.py
fhir_types/FHIR_AllergyIntolerance_Reaction.py
fhir_types/FHIR_Annotation.py
fhir_types/FHIR_Appointment.py
fhir_types/FHIR_AppointmentResponse.py
fhir_types/FHIR_Appointment_Participant.py
fhir_types/FHIR_Attachment.py
fhir_types/FHIR_AuditEvent.py
fhir_types/FHIR_AuditEvent_Agent.py
fhir_types/FHIR_AuditEvent_Detail.py
fhir_types/FHIR_AuditEvent_Entity.py
fhir_types/FHIR_AuditEvent_Network.py
fhir_types/FHIR_AuditEvent_Source.py
fhir_types/FHIR_Basic.py
fhir_types/FHIR_Binary.py
fhir_types/FHIR_BiologicallyDerivedProduct.py
fhir_types/FHIR_BiologicallyDerivedProduct_Collection.py
fhir_types/FHIR_BiologicallyDerivedProduct_Manipulation.py
fhir_types/FHIR_BiologicallyDerivedProduct_Processing.py
fhir_types/FHIR_BiologicallyDerivedProduct_Storage.py
fhir_types/FHIR_BodyStructure.py
fhir_types/FHIR_Bundle.py
fhir_types/FHIR_Bundle_Entry.py
fhir_types/FHIR_Bundle_Link.py
fhir_types/FHIR_Bundle_Request.py
fhir_types/FHIR_Bundle_Response.py
fhir_types/FHIR_Bundle_Search.py
fhir_types/FHIR_CapabilityStatement.py
fhir_types/FHIR_CapabilityStatement_Document.py
fhir_types/FHIR_CapabilityStatement_Endpoint.py
fhir_types/FHIR_CapabilityStatement_Implementation.py
fhir_types/FHIR_CapabilityStatement_Interaction.py
fhir_types/FHIR_CapabilityStatement_Interaction1.py
fhir_types/FHIR_CapabilityStatement_Messaging.py
fhir_types/FHIR_CapabilityStatement_Operation.py
fhir_types/FHIR_CapabilityStatement_Resource.py
fhir_types/FHIR_CapabilityStatement_Rest.py
fhir_types/FHIR_CapabilityStatement_SearchParam.py
fhir_types-0.2.4.dist-info/LICENSE.md
fhir_types-0.2.4.dist-info/METADATA
fhir_types-0.2.4.dist-info/WHEEL
fhir_types-0.2.4.dist-info/top_level.txt
fhir_types-0.2.4.dist-info/RECORD
