Metadata-Version: 2.1
Name: fhir-types
Version: 0.2.4
Summary: Types for FHIR Resources
Author: Anthem Inc
License: Apache
Keywords: FHIR
Platform: UNKNOWN
Requires-Python: >=3.8
License-File: LICENSE.md
